ncos/__init__.py
ncos/module.py
ncos/commons/__init__.py
ncos/networks/__init__.py
ncos/networks/mqtt.py
ncos/utils/__init__.py
ncos/utils/logger.py
pyncos_module-0.0.15.dist-info/LICENSE.txt
pyncos_module-0.0.15.dist-info/METADATA
pyncos_module-0.0.15.dist-info/WHEEL
pyncos_module-0.0.15.dist-info/top_level.txt
pyncos_module-0.0.15.dist-info/RECORD
