Metadata-Version: 2.1
Name: pyncos-module
Version: 0.0.15
Home-page: https://gitee.com/zwsjz/carbot-module-lib
Author: xuwh
Author-email: xuwhdev@gmail.com
Classifier: Programming Language :: Python :: 3.10
Classifier: License :: OSI Approved :: MIT License
Classifier: Operating System :: OS Independent
Requires-Python: >=3.10
License-File: LICENSE.txt
Requires-Dist: pyserial >=3.5
Requires-Dist: paho-mqtt >=1.6.1
